LICENSE
ocean_spark/__init__.py
ocean_spark/application_state.py
ocean_spark/connect/__init__.py
ocean_spark/connect/hook.py
ocean_spark/connect/inverse_websockify.py
ocean_spark/connect/operator.py
ocean_spark/extra_links.py
ocean_spark/hooks.py
ocean_spark/operators.py
ocean_spark/plugins.py
ocean_spark/response.py
ocean_spark_airflow_provider-1.1.4.dist-info/LICENSE
ocean_spark_airflow_provider-1.1.4.dist-info/METADATA
ocean_spark_airflow_provider-1.1.4.dist-info/WHEEL
ocean_spark_airflow_provider-1.1.4.dist-info/entry_points.txt
ocean_spark_airflow_provider-1.1.4.dist-info/RECORD
