Metadata-Version: 2.1
Name: ocean-spark-airflow-provider
Version: 1.1.4
Summary: Apache Airflow connector for Ocean for Apache Spark
Home-page: https://spot.io/products/ocean-apache-spark/
License: Apache-2.0
Keywords: airflow,provider,spark,ocean
Author: Ocean for Apache Spark authors
Author-email: clement.rezvoy@netapp.com
Requires-Python: >=3.7,<4.0
Classifier: Development Status :: 4 - Beta
Classifier: License :: OSI Approved :: Apache Software License
Classifier: Operating System :: OS Independent
Classifier: Programming Language :: Python :: 3
Classifier: Programming Language :: Python :: 3.7
Classifier: Programming Language :: Python :: 3.8
Classifier: Programming Language :: Python :: 3.9
Classifier: Programming Language :: Python :: 3.10
Classifier: Programming Language :: Python :: 3.11
Classifier: Programming Language :: Python :: 3.12
Requires-Dist: apache-airflow (>=1)
Requires-Dist: googleapis-common-protos (>=1.56.4) ; python_version >= "3.8" and python_version < "4.0"
Requires-Dist: grpcio (>=1.50.0) ; python_version >= "3.8" and python_version < "4.0"
Requires-Dist: grpcio-status (>=1.48.2) ; python_version >= "3.8" and python_version < "4.0"
Requires-Dist: packaging (>=20.9)
Requires-Dist: pandas (>=1.5.1) ; python_version >= "3.8" and python_version < "4.0"
Requires-Dist: pyarrow ; python_version >= "3.8" and python_version < "4.0"
Requires-Dist: pyspark (>=3.3.1) ; python_version >= "3.8" and python_version < "4.0"
Requires-Dist: requests (>=2.0.0,<3.0.0)
Requires-Dist: websockets (>=13.0.1,<14.0.0) ; python_version >= "3.8" and python_version < "4.0"
Project-URL: Repository, https://github.com/spotinst/ocean-spark-airflow-provider
